MANIFEST.in
README.md
setup.py
django_http_log/__init__.py
django_http_log/apps.py
django_http_log/models.py
django_http_log/views.py
django_http_log.egg-info/PKG-INFO
django_http_log.egg-info/SOURCES.txt
django_http_log.egg-info/dependency_links.txt
django_http_log.egg-info/requires.txt
django_http_log.egg-info/top_level.txt
django_http_log/common/__init__.py
django_http_log/common/jwt.py
django_http_log/common/request.py
django_http_log/common/response.py
django_http_log/decorator/__init__.py
django_http_log/decorator/auth.py
django_http_log/serializers/__init__.py