Metadata-Version: 2.1
Name: django-http-log
Version: 0.1.4
Summary: 记录django, http请求日志，并存到mongodb中
Home-page: https://gitee.com/zhsjch/django_http_log.git
Author: JiChaoSong
Author-email: jichaosong@outlook.com
License: UNKNOWN
Platform: UNKNOWN
